surge/__init__.py
surge/__version__.py
surge/cli.py
surge/core/__init__.py
surge/core/docs.py
surge/core/monitor.py
surge/core/pipeline_runner.py
surge/core/worker.py
surge/lib/__init__.py
surge/lib/path.py
surge/lib/topic.py
surge/lib/util.py
surge/static/favicon.png
surge/static/redoc.standalone.js
surge/static/swagger-ui-bundle.js
surge/static/swagger-ui.css
talus_surge-1.1.2b3.dist-info/METADATA
talus_surge-1.1.2b3.dist-info/WHEEL
talus_surge-1.1.2b3.dist-info/entry_points.txt
talus_surge-1.1.2b3.dist-info/RECORD
