Metadata-Version: 2.4
Name: talus-surge
Version: 1.1.2b3
Summary: An external background task execution framework for eastwind.
Project-URL: Homepage, https://autosoftint.com
Project-URL: Documentation, https://autosoftint.com/developer/documentation/surge
Project-URL: Repository, https://autosoftint.com/git/talus/surge
Project-URL: Bug Tracker, https://autosoftint.com/git/talus/surge/issues
Author-email: "ASI Pty. Ltd." <asi.au@outlook.com>, Saki Tojo <tomguts@126.com>
Maintainer-email: "ASI Pty. Ltd." <asi.au@outlook.com>, Saki Tojo <tomguts@126.com>
License-Expression: LicenseRef-Proprietary
Classifier: Development Status :: 4 - Beta
Classifier: Intended Audience :: Developers
Classifier: Programming Language :: Python :: 3
Requires-Python: >=3.11
Requires-Dist: talus-eastwind
